sika/__init__.py
sika/main.py
sika/db/__init__.py
sika/db/sql_db_handler.py
sika/task_bypass/__init__.py
sika/task_bypass/allocate_stage_tasks.py
sika/task_bypass/categorize_task.py
sika/task_bypass/concat_content.py
sika/task_bypass/filter_content.py
sika/task_bypass/helpers.py
sika/task_bypass/merge_tasks.py
sika/task_bypass/read_content.py
sika/task_bypass/run_stages.py
sika/task_bypass/transform_content.py
sika/task_bypass/tasktypes/__init__.py
sika/task_bypass/tasktypes/filter/__init__.py
sika/task_bypass/tasktypes/filter/json_path.py
sika/task_bypass/tasktypes/filter/sql.py
sika/task_bypass/tasktypes/filter/xpath.py
sika/task_bypass/tasktypes/merge/__init__.py
sika/task_bypass/tasktypes/merge/sql_merge.py
sika/task_bypass/tasktypes/read/__init__.py
sika/task_bypass/tasktypes/read/http_request.py
sika/task_bypass/tasktypes/transform/__init__.py
sika/task_bypass/tasktypes/transform/decompress_content.py
sika/task_bypass/tasktypes/transform/flatten_lists_to_dataframe.py
sika/task_bypass/tasktypes/transform/rename_columns.py
sika/task_bypass/tasktypes/transform/sampling.py
sika/task_bypass/tasktypes/transform/split_dataframe_rows.py
sika/task_bypass/tasktypes/transform/string_injecting.py
sika/task_bypass/tasktypes/transform/sub_selection.py
sika/task_bypass/tasktypes/transform/transform_to_dataframe.py
tests/__init__.py
tests/handler.py
tests/test_filter.py
tests/test_merge.py
tests/test_read.py
tests/test_stages.py
tests/test_tasks.py
tests/test_transform.py
DataSika-1.0.3.dist-info/LICENSE
DataSika-1.0.3.dist-info/METADATA
DataSika-1.0.3.dist-info/WHEEL
DataSika-1.0.3.dist-info/entry_points.txt
DataSika-1.0.3.dist-info/top_level.txt
DataSika-1.0.3.dist-info/RECORD
