Metadata-Version: 2.1
Name: DataSika
Version: 1.0.3
Summary: Package for building pipeline by yaml file
Home-page: https://github.com/rainyjonne/DataSika
Author: rainyjonne
Author-email: rainyjonne@gmail.com
License: MIT
Project-URL: Bug Tracker, https://github.com/rainyjonne/DataSika/issues
Keywords: sika data pipeline
Platform: UNKNOWN
Classifier: Programming Language :: Python :: 3
Classifier: License :: OSI Approved :: MIT License
Classifier: Operating System :: OS Independent
License-File: LICENSE
Requires-Dist: certifi (==2021.10.8)
Requires-Dist: charset-normalizer (==2.0.12)
Requires-Dist: idna (==3.3)
Requires-Dist: lxml (==4.8.0)
Requires-Dist: pandas (==1.3)
Requires-Dist: numpy (==1.17.3)
Requires-Dist: python-dateutil (==2.8.2)
Requires-Dist: pytz (==2021.3)
Requires-Dist: PyYAML (==6.0)
Requires-Dist: six (==1.16.0)
Requires-Dist: sqldf (==0.4.2)
Requires-Dist: urllib3 (==1.26.8)
Requires-Dist: pandasql (==0.7.3)
Requires-Dist: ipython (==7.32.0)
Requires-Dist: jsonpath-ng (==1.5.3)
Requires-Dist: requests-futures (==1.0.0)
Requires-Dist: pytest (==7.1.2)
Requires-Dist: pytest-vcr (==1.0.2)
Requires-Dist: argparse (==1.4.0)
Requires-Dist: wheel (==0.37.1)
